stringpath.py
stringpath-1.0.0.dist-info/LICENSE
stringpath-1.0.0.dist-info/METADATA
stringpath-1.0.0.dist-info/WHEEL
stringpath-1.0.0.dist-info/top_level.txt
stringpath-1.0.0.dist-info/RECORD
