Metadata-Version: 2.1
Name: stringpath
Version: 1.0.0
Summary: StringPath for simulating a 'cd' command in a path-like string
Author: Pascal Vallaster
Classifier: Programming Language :: Python :: 3
Classifier: License :: OSI Approved :: MIT License
Classifier: Operating System :: OS Independent
Requires-Python: >=3.4
License-File: LICENSE
